mongo2json/__init__.py
mongo2json/cleaner.py
mongo2json/mongo2json.py
mongo2json-1.0.0.dist-info/LICENSE
mongo2json-1.0.0.dist-info/METADATA
mongo2json-1.0.0.dist-info/WHEEL
mongo2json-1.0.0.dist-info/top_level.txt
mongo2json-1.0.0.dist-info/RECORD
